[
	{
		"type": "title"
	},
	{
		"type": "group",
		"name": "Género",
		"filters": [
			{
				"type": "genre",
				"name": "Acción",
				"id": "4",
				"canExclude": true
			},
			{
				"type": "genre",
				"name": "Apocalíptico",
				"id": "62",
				"canExclude": true
			},
			{
				"type": "genre",
				"name": "Artes Marciales",
				"id": "6",
				"canExclude": true
			},
			{
				"type": "genre",
				"name": "Aventura",
				"id": "7",
				"canExclude": true
			},
			{
				"type": "genre",
				"name": "Bélico",
				"id": "92",
				"canExclude": true
			},
			{
				"type": "genre",
				"name": "Science fiction",
				"id": "-36",
				"canExclude": true
			},
			{
				"type": "genre",
				"name": "Cocina",
				"id": "89",
				"canExclude": true
			},
			{
				"type": "genre",
				"name": "Comedia",
				"id": "5",
				"canExclude": true
			},
			{
				"type": "genre",
				"name": "Crimen",
				"id": "24",
				"canExclude": true
			},
			{
				"type": "genre",
				"name": "Drama",
				"id": "18",
				"canExclude": true
			},
			{
				"type": "genre",
				"name": "Ecchi",
				"id": "15",
				"canExclude": true
			},
			{
				"type": "genre",
				"name": "Fantasía",
				"id": "43",
				"canExclude": true
			},
			{
				"type": "genre",
				"name": "Harem",
				"id": "11",
				"canExclude": true
			},
			{
				"type": "genre",
				"name": "Histórico",
				"id": "48",
				"canExclude": true
			},
			{
				"type": "genre",
				"name": "Isekai",
				"id": "50",
				"canExclude": true
			},
			{
				"type": "genre",
				"name": "Josei",
				"id": "56",
				"canExclude": true
			},
			{
				"type": "genre",
				"name": "Magia",
				"id": "32",
				"canExclude": true
			},
			{
				"type": "genre",
				"name": "Mecha",
				"id": "35",
				"canExclude": true
			},
			{
				"type": "genre",
				"name": "Misterio",
				"id": "25",
				"canExclude": true
			},
			{
				"type": "genre",
				"name": "Psicológico",
				"id": "20",
				"canExclude": true
			},
			{
				"type": "genre",
				"name": "Realidad Virtual",
				"id": "88",
				"canExclude": true
			},
			{
				"type": "genre",
				"name": "Recuentos de la vida",
				"id": "90",
				"canExclude": true
			},
			{
				"type": "genre",
				"name": "Reencarnación",
				"id": "13",
				"canExclude": true
			},
			{
				"type": "genre",
				"name": "Romance",
				"id": "12",
				"canExclude": true
			},
			{
				"type": "genre",
				"name": "Seinen",
				"id": "19",
				"canExclude": true
			},
			{
				"type": "genre",
				"name": "Shoujo",
				"id": "26",
				"canExclude": true
			},
			{
				"type": "genre",
				"name": "Shounen",
				"id": "8",
				"canExclude": true
			},
			{
				"type": "genre",
				"name": "Sobrenatural",
				"id": "87",
				"canExclude": true
			},
			{
				"type": "genre",
				"name": "Superpoderes",
				"id": "111",
				"canExclude": true
			},
			{
				"type": "genre",
				"name": "Terror",
				"id": "17",
				"canExclude": true
			},
			{
				"type": "genre",
				"name": "Thriller",
				"id": "27",
				"canExclude": true
			},
			{
				"type": "genre",
				"name": "Tragedia",
				"id": "21",
				"canExclude": true
			},
			{
				"type": "genre",
				"name": "Transmigración",
				"id": "97",
				"canExclude": true
			},
			{
				"type": "genre",
				"name": "Viaje en el Tiempo",
				"id": "84",
				"canExclude": true
			},
			{
				"type": "genre",
				"name": "Vida Escolar",
				"id": "45",
				"canExclude": true
			},
			{
				"type": "genre",
				"name": "Vida urbana",
				"id": "107",
				"canExclude": true
			},
			{
				"type": "genre",
				"name": "Videojuegos",
				"id": "38",
				"canExclude": true
			}
		]
	},
	{
		"type": "select",
		"name": "Status",
		"options": [
			"All",
			"Ongoing",
			"Completed",
			"Hiatus"
		]
	},
	{
		"type": "select",
		"name": "Type",
		"options": [
			"All",
			"Manga",
			"Manhwa",
			"Manhua",
			"Comic"
		]
	}
]
