[
	{
		"type": "title"
	},
	{
		"type": "sort",
		"name": "Order By",
		"options": [
			"Rating",
			"Update",
			"Latest",
			"Z-A",
			"A-Z"
		],
		"default": {
			"index": 1
		}
	},
	{
		"type": "select",
		"name": "Status",
		"options": [
			"All",
			"Ongoing",
			"Hiatus",
			"Completed",
			"Dropped",
			"Season End",
			"Coming Soon"
		],
		"default": 0
	},
	{
		"type": "select",
		"name": "Type",
		"options": [
			"All",
			"Manhwa",
			"Manhua",
			"Manga"
		],
		"default": 0
	},
	{
		"type": "group",
		"name": "Genres",
		"filters": [
			{
				"type": "genre",
				"name": "Action",
				"id": "1"
			},
			{
				"type": "genre",
				"name": "Adaptation",
				"id": "2"
			},
			{
				"type": "genre",
				"name": "Adult",
				"id": "3"
			},
			{
				"type": "genre",
				"name": "Adventure",
				"id": "4"
			},
			{
				"type": "genre",
				"name": "Another chance",
				"id": "5"
			},
			{
				"type": "genre",
				"name": "Apocalypse",
				"id": "6"
			},
			{
				"type": "genre",
				"name": "Comedy",
				"id": "7"
			},
			{
				"type": "genre",
				"name": "Coming Soon",
				"id": "8"
			},
			{
				"type": "genre",
				"name": "Crazy MC",
				"id": "9"
			},
			{
				"type": "genre",
				"name": "Cultivation",
				"id": "10"
			},
			{
				"type": "genre",
				"name": "Cute",
				"id": "11"
			},
			{
				"type": "genre",
				"name": "Demon",
				"id": "12"
			},
			{
				"type": "genre",
				"name": "Drama",
				"id": "13"
			},
			{
				"type": "genre",
				"name": "Dungeons",
				"id": "14"
			},
			{
				"type": "genre",
				"name": "Ecchi",
				"id": "15"
			},
			{
				"type": "genre",
				"name": "Fantasy",
				"id": "16"
			},
			{
				"type": "genre",
				"name": "Fight",
				"id": "17"
			},
			{
				"type": "genre",
				"name": "Game",
				"id": "18"
			},
			{
				"type": "genre",
				"name": "Genius",
				"id": "19"
			},
			{
				"type": "genre",
				"name": "Genius MC",
				"id": "20"
			},
			{
				"type": "genre",
				"name": "Harem",
				"id": "21"
			},
			{
				"type": "genre",
				"name": "Hero",
				"id": "22"
			},
			{
				"type": "genre",
				"name": "Historical",
				"id": "23"
			},
			{
				"type": "genre",
				"name": "Isekai",
				"id": "24"
			},
			{
				"type": "genre",
				"name": "Josei",
				"id": "25"
			},
			{
				"type": "genre",
				"name": "Kool Kids",
				"id": "26"
			},
			{
				"type": "genre",
				"name": "Loli",
				"id": "27"
			},
			{
				"type": "genre",
				"name": "Magic",
				"id": "28"
			},
			{
				"type": "genre",
				"name": "Martial Arts",
				"id": "29"
			},
			{
				"type": "genre",
				"name": "Mature",
				"id": "30"
			},
			{
				"type": "genre",
				"name": "Mecha",
				"id": "31"
			},
			{
				"type": "genre",
				"name": "Modern Setting",
				"id": "32"
			},
			{
				"type": "genre",
				"name": "Monsters",
				"id": "33"
			},
			{
				"type": "genre",
				"name": "Murim",
				"id": "34"
			},
			{
				"type": "genre",
				"name": "Mystery",
				"id": "35"
			},
			{
				"type": "genre",
				"name": "Necromancer",
				"id": "36"
			},
			{
				"type": "genre",
				"name": "Noble",
				"id": "37"
			},
			{
				"type": "genre",
				"name": "Overpowered",
				"id": "38"
			},
			{
				"type": "genre",
				"name": "Pets",
				"id": "39"
			},
			{
				"type": "genre",
				"name": "Post-Apocalyptic",
				"id": "40"
			},
			{
				"type": "genre",
				"name": "Psychological",
				"id": "41"
			},
			{
				"type": "genre",
				"name": "Rebirth",
				"id": "42"
			},
			{
				"type": "genre",
				"name": "Regression",
				"id": "43"
			},
			{
				"type": "genre",
				"name": "Reincarnation",
				"id": "44"
			},
			{
				"type": "genre",
				"name": "Return",
				"id": "45"
			},
			{
				"type": "genre",
				"name": "Returned",
				"id": "46"
			},
			{
				"type": "genre",
				"name": "Returner",
				"id": "47"
			},
			{
				"type": "genre",
				"name": "Revenge",
				"id": "48"
			},
			{
				"type": "genre",
				"name": "Romance",
				"id": "49"
			},
			{
				"type": "genre",
				"name": "School",
				"id": "50"
			},
			{
				"type": "genre",
				"name": "School Life",
				"id": "51"
			},
			{
				"type": "genre",
				"name": "Sci-fi",
				"id": "52"
			},
			{
				"type": "genre",
				"name": "Seinen",
				"id": "53"
			},
			{
				"type": "genre",
				"name": "Shoujo",
				"id": "54"
			},
			{
				"type": "genre",
				"name": "Shounen",
				"id": "55"
			},
			{
				"type": "genre",
				"name": "Slice of Life",
				"id": "56"
			},
			{
				"type": "genre",
				"name": "Sports",
				"id": "57"
			},
			{
				"type": "genre",
				"name": "Super Hero",
				"id": "58"
			},
			{
				"type": "genre",
				"name": "Superhero",
				"id": "59"
			},
			{
				"type": "genre",
				"name": "Supernatural",
				"id": "60"
			},
			{
				"type": "genre",
				"name": "Survival",
				"id": "61"
			},
			{
				"type": "genre",
				"name": "Suspense",
				"id": "62"
			},
			{
				"type": "genre",
				"name": "System",
				"id": "63"
			},
			{
				"type": "genre",
				"name": "Thriller",
				"id": "64"
			},
			{
				"type": "genre",
				"name": "Time Travel",
				"id": "65"
			},
			{
				"type": "genre",
				"name": "Time Travel (Future)",
				"id": "66"
			},
			{
				"type": "genre",
				"name": "Tower",
				"id": "67"
			},
			{
				"type": "genre",
				"name": "Tragedy",
				"id": "68"
			},
			{
				"type": "genre",
				"name": "Transmigrating",
				"id": "69"
			},
			{
				"type": "genre",
				"name": "Video Game",
				"id": "70"
			},
			{
				"type": "genre",
				"name": "Video Games",
				"id": "71"
			},
			{
				"type": "genre",
				"name": "Villain",
				"id": "72"
			},
			{
				"type": "genre",
				"name": "Violence",
				"id": "73"
			},
			{
				"type": "genre",
				"name": "Virtual Game",
				"id": "74"
			},
			{
				"type": "genre",
				"name": "Virtual Reality",
				"id": "75"
			},
			{
				"type": "genre",
				"name": "Virtual World",
				"id": "76"
			},
			{
				"type": "genre",
				"name": "Webtoon",
				"id": "77"
			},
			{
				"type": "genre",
				"name": "Wuxia",
				"id": "78"
			}
		]
	}
]
